odoo8_addon_product_barcode_generator-8.0.1.0.0.99.dev30-py3.8-nspkg.pth
odoo_addons/product_barcode_generator/README.rst
odoo_addons/product_barcode_generator/__init__.py
odoo_addons/product_barcode_generator/__openerp__.py
odoo_addons/product_barcode_generator/data/ean_sequence.xml
odoo_addons/product_barcode_generator/i18n/am.po
odoo_addons/product_barcode_generator/i18n/ar.po
odoo_addons/product_barcode_generator/i18n/ca.po
odoo_addons/product_barcode_generator/i18n/da.po
odoo_addons/product_barcode_generator/i18n/de.po
odoo_addons/product_barcode_generator/i18n/el_GR.po
odoo_addons/product_barcode_generator/i18n/es.po
odoo_addons/product_barcode_generator/i18n/es_ES.po
odoo_addons/product_barcode_generator/i18n/es_MX.po
odoo_addons/product_barcode_generator/i18n/eu.po
odoo_addons/product_barcode_generator/i18n/fi.po
odoo_addons/product_barcode_generator/i18n/fr.po
odoo_addons/product_barcode_generator/i18n/fr_CA.po
odoo_addons/product_barcode_generator/i18n/fr_CH.po
odoo_addons/product_barcode_generator/i18n/fr_FR.po
odoo_addons/product_barcode_generator/i18n/gl.po
odoo_addons/product_barcode_generator/i18n/hr.po
odoo_addons/product_barcode_generator/i18n/hr_HR.po
odoo_addons/product_barcode_generator/i18n/id.po
odoo_addons/product_barcode_generator/i18n/it.po
odoo_addons/product_barcode_generator/i18n/nb.po
odoo_addons/product_barcode_generator/i18n/nb_NO.po
odoo_addons/product_barcode_generator/i18n/nl.po
odoo_addons/product_barcode_generator/i18n/nl_BE.po
odoo_addons/product_barcode_generator/i18n/nl_NL.po
odoo_addons/product_barcode_generator/i18n/product_barcode_generator.pot
odoo_addons/product_barcode_generator/i18n/pt.po
odoo_addons/product_barcode_generator/i18n/pt_BR.po
odoo_addons/product_barcode_generator/i18n/ro.po
odoo_addons/product_barcode_generator/i18n/ru.po
odoo_addons/product_barcode_generator/i18n/sk.po
odoo_addons/product_barcode_generator/i18n/sl.po
odoo_addons/product_barcode_generator/i18n/tr.po
odoo8_addon_product_barcode_generator-8.0.1.0.0.99.dev30.dist-info/METADATA
odoo8_addon_product_barcode_generator-8.0.1.0.0.99.dev30.dist-info/WHEEL
odoo8_addon_product_barcode_generator-8.0.1.0.0.99.dev30.dist-info/namespace_packages.txt
odoo8_addon_product_barcode_generator-8.0.1.0.0.99.dev30.dist-info/top_level.txt
odoo8_addon_product_barcode_generator-8.0.1.0.0.99.dev30.dist-info/RECORD
