Metadata-Version: 2.1
Name: odoo8-addon-product-barcode-generator
Version: 8.0.1.0.0.99.dev30
Summary: Product barcode generator
Home-page: http://www.julius.fr/
Author: Julius Network Solutions, Odoo Community Association (OCA)
Author-email: support@odoo-community.org
License: GPL-3
Platform: UNKNOWN
Classifier: Programming Language :: Python
Classifier: Framework :: Odoo
Classifier: Framework :: Odoo :: 8.0
Classifier: License :: OSI Approved :: GNU General Public License v3 (GPLv3)
Requires-Python: ~=2.7
Requires-Dist: odoo (<9.0a,>=8.0a)
